zohencel_ai/__init__.py
zohencel_ai/analysis/__init__.py
zohencel_ai/analysis/app.py
zohencel_ai/analysis/chart_bot.py
zohencel_ai/analysis/templates.py
zohencel_ai/assistant/Grog_streaming.py
zohencel_ai/assistant/__init__.py
zohencel_ai/assistant/voice_assistant.py
zohencel_ai/chatbot/__init__.py
zohencel_ai/chatbot/chat_manager.py
zohencel_ai/mlbot/__init__.py
zohencel_ai/mlbot/bot.py
zohencel_ai/mlbot/common.py
zohencel_ai/mlbot/main.py
zohencel_ai/mlbot/template_class.py
zohencel_ai/mlbot/test_script.py
zohencel_ai/utils/__init__.py
zohencel_ai-0.4.49.dist-info/licenses/LICENSE
zohencel_ai-0.4.49.dist-info/METADATA
zohencel_ai-0.4.49.dist-info/WHEEL
zohencel_ai-0.4.49.dist-info/top_level.txt
zohencel_ai-0.4.49.dist-info/RECORD
