Metadata-Version: 2.4
Name: zohencel-ai
Version: 0.4.49
Summary: World's first 'Text to ML model' support library. Also comes with an analysis chart bot that plots graphs from your data through queries and a completely customizable AI voice assistant.
Home-page: https://zohencelai.github.io/
Author: Vishnu K
Author-email: vishnuknandanam@gmail.com
Classifier: Programming Language :: Python :: 3
Classifier: License :: OSI Approved :: MIT License
Classifier: Operating System :: OS Independent
Requires-Python: >=3.9
License-File: LICENSE
Requires-Dist: numpy
Requires-Dist: requests
Requires-Dist: assemblyai
Requires-Dist: playsound
Requires-Dist: PyAudio
Requires-Dist: pyttsx3
Requires-Dist: SpeechRecognition
Requires-Dist: groq
Requires-Dist: pillow
Requires-Dist: matplotlib
Requires-Dist: streamlit
Requires-Dist: pandas
Requires-Dist: seaborn
Requires-Dist: fastapi
Requires-Dist: uvicorn
Requires-Dist: scikit-learn
Requires-Dist: black
Requires-Dist: python-multipart
Dynamic: author
Dynamic: author-email
Dynamic: classifier
Dynamic: description
Dynamic: description-content-type
Dynamic: home-page
Dynamic: license-file
Dynamic: requires-dist
Dynamic: requires-python
Dynamic: summary
